MANIFEST.in
README.md
setup.py
django_mp_reviews.egg-info/PKG-INFO
django_mp_reviews.egg-info/SOURCES.txt
django_mp_reviews.egg-info/dependency_links.txt
django_mp_reviews.egg-info/top_level.txt
reviews/__init__.py
reviews/admin.py
reviews/apps.py
reviews/forms.py
reviews/models.py
reviews/urls.py
reviews/views.py
reviews/locale/ru/LC_MESSAGES/django.mo
reviews/locale/ru/LC_MESSAGES/django.po
reviews/locale/uk/LC_MESSAGES/django.mo
reviews/locale/uk/LC_MESSAGES/django.po
reviews/migrations/0001_initial.py
reviews/migrations/0002_review_answer.py
reviews/migrations/__init__.py
reviews/static/jquery.rateit/delete.gif
reviews/static/jquery.rateit/jquery.rateit.js
reviews/static/jquery.rateit/rateit.css
reviews/static/jquery.rateit/star.gif
reviews/templates/reviews/email.html
reviews/templates/reviews/list.html
reviews/templates/reviews/modal.html
reviews/templatetags/__init__.py
reviews/templatetags/reviews.py