Metadata-Version: 2.1
Name: django-mp-reviews
Version: 6.0.1
Summary: Django reviews apps
Home-page: https://github.com/pmaigutyak/mp-reviews
Author: Paul Maigutyak
Author-email: pmaigutyak@gmail.com
License: MIT
Download-URL: https://github.com/pmaigutyak/mp-reviews/archive/6.0.1.tar.gz
Platform: UNKNOWN
